{
  "Game:427be455-b125-4b47-8b93-381a9eb2d0a8": {
    "home": "Charlotte FC",
    "away": "Philadelphia Union",
    "date": "2026-04-04",
    "home_goals": 2,
    "away_goals": 1,
    "home_scorers": [],
    "away_scorers": [],
    "home_assists": [],
    "away_assists": []
  },
  "Game:d67472a8-7195-46f2-abbd-8a4e86e1bec6": {
    "home": "Cruz Azul FC",
    "away": "Los Angeles FC",
    "date": "2026-04-15",
    "home_goals": 1,
    "away_goals": 1,
    "home_scorers": [],
    "away_scorers": [],
    "home_assists": [],
    "away_assists": []
  },
  "Game:367ed2f3-4dfc-4b26-b6cf-4dd4d42322e7": {
    "home": "Atlanta United",
    "away": "Nashville SC",
    "date": "2026-04-18",
    "home_goals": 0,
    "away_goals": 2,
    "home_scorers": [],
    "away_scorers": [],
    "home_assists": [],
    "away_assists": []
  },
  "Game:1c5ec81c-e6c5-439c-920a-e86960102297": {
    "home": "Real Salt Lake",
    "away": "Inter Miami CF",
    "date": "2026-04-23",
    "home_goals": 0,
    "away_goals": 2,
    "home_scorers": [],
    "away_scorers": [],
    "home_assists": [],
    "away_assists": []
  },
  "Game:ba4b32be-9316-4c0a-8469-1d20b2b30396": {
    "home": "Red Star FC 93",
    "away": "En Avant Guingamp",
    "date": "2026-04-24",
    "home_goals": 3,
    "away_goals": 2,
    "home_scorers": [],
    "away_scorers": [],
    "home_assists": [],
    "away_assists": []
  }
}